{
    "summary": "",
    "tags": "",
    "cWarning": false,
    "cWarningAdditions": "",
    "poemName": "Stuff On The Iso",
    "poemAuthor": "Zekiah",
    "poemContent": {
        "type": "fragment",
        "styles": [],
        "children": [
            {
                "type": "text",
                "content": "We know nothing, we build our saunas broad. "
            },
            {
                "type": "newline",
                "count": 1
            },
            {
                "type": "text",
                "content": "Broad and tall, just like the reptillians that roam the earth, "
            },
            {
                "type": "newline",
                "count": 1
            },
            {
                "type": "text",
                "content": "and the white froths that beat at our lagoons. "
            },
            {
                "type": "newline",
                "count": 2
            },
            {
                "type": "text",
                "content": "Huawei has never threatened us, "
            },
            {
                "type": "newline",
                "count": 1
            },
            {
                "type": "text",
                "content": "yet we know that they lie beneath, "
            },
            {
                "type": "newline",
                "count": 1
            },
            {
                "type": "text",
                "content": "in colossal chrome canisters of crap; a natural home - "
            },
            {
                "type": "newline",
                "count": 2
            },
            {
                "type": "text",
                "content": "Ready to summon a storm, of sedimentary sewage and "
            },
            {
                "type": "newline",
                "count": 1
            },
            {
                "type": "text",
                "content": "dead fish bones. "
            },
            {
                "type": "newline",
                "count": 2
            },
            {
                "type": "text",
                "content": "Produced by us. "
            },
            {
                "type": "newline",
                "count": 2
            },
            {
                "type": "text",
                "content": "Carbon particulates rain down on the grilli, simmering, "
            },
            {
                "type": "newline",
                "count": 1
            },
            {
                "type": "text",
                "content": "smoking, and burning through the sausages. "
            },
            {
                "type": "newline",
                "count": 1
            },
            {
                "type": "text",
                "content": "Rain turns yellow as each sceptic tank blows full, "
            },
            {
                "type": "newline",
                "count": 1
            },
            {
                "type": "text",
                "content": "reducing the iso to a mound of crap and flies. "
            },
            {
                "type": "newline",
                "count": 2
            },
            {
                "type": "text",
                "content": "Yet, "
            },
            {
                "type": "newline",
                "count": 1
            },
            {
                "type": "text",
                "content": "it is a giant seagull which we still fear? "
            },
            {
                "type": "newline",
                "count": 2
            }
        ]
    },
    "pageStyle": "centre",
    "pageBackground": ""
}